{
	"class" : {
		"for:on:" : "ms 5/21/2019 11:15",
		"transitionColor" : "ms 5/21/2019 09:44" },
	"instance" : {
		"addHandles" : "ms 5/21/2019 10:18",
		"applyViewData:" : "ms 5/13/2019 15:33",
		"buildViewData" : "ms 5/13/2019 15:01",
		"delete" : "ms 5/13/2019 12:02",
		"depth" : "ms 5/6/2019 15:37",
		"dropVertex:event:fromHandle:" : "ms 5/6/2019 16:34",
		"endDock" : "ms 4/30/2019 15:54",
		"endDock:" : "ms 4/30/2019 15:54",
		"endPosition" : "ms 5/20/2019 15:16",
		"endState" : "ms 4/30/2019 16:07",
		"endState:" : "ms 5/7/2019 15:25",
		"endStateMorph" : "ms 4/30/2019 16:06",
		"hideHandles" : "ms 5/7/2019 15:49",
		"initialize" : "ms 5/21/2019 09:56",
		"initializeWith:" : "ms 5/21/2019 11:15",
		"labelPosition" : "ms 5/7/2019 15:33",
		"nameMorph" : "ms 4/30/2019 16:30",
		"nameMorph:" : "ms 4/30/2019 16:30",
		"reattachVertex:" : "ms 5/7/2019 15:16",
		"setVertexState:to:dock:" : "ms 5/13/2019 15:40",
		"showHandles" : "ms 5/7/2019 15:49",
		"startDock" : "ms 4/30/2019 15:54",
		"startDock:" : "ms 4/30/2019 15:54",
		"startPosition" : "ms 5/20/2019 15:16",
		"startState" : "ms 4/30/2019 16:06",
		"startState:" : "ms 5/6/2019 16:55",
		"startStateMorph" : "ms 4/30/2019 16:06",
		"state" : "ms 4/30/2019 16:06",
		"stateMachineMorph" : "ms 4/30/2019 16:01",
		"stateMachineMorph:" : "ms 5/21/2019 10:30",
		"stateTransitionAssoc" : "ms 4/30/2019 16:04",
		"stateTransitionAssoc:" : "ms 5/21/2019 10:33",
		"transition" : "ms 5/21/2019 10:33",
		"update:" : "ms 5/13/2019 16:11",
		"updateVertices" : "ms 5/6/2019 16:11" } }
