{
	"class" : {
		"open" : "LB 4/11/2019 10:52" },
	"instance" : {
		"addGameObject:" : "WoC 4/9/2019 11:59",
		"allGameObjects" : "WoC 4/8/2019 09:51",
		"applyUserInput" : "WoC 4/5/2019 13:59",
		"background" : "BD 4/4/2019 12:08",
		"background:" : "BD 4/4/2019 12:08",
		"drawGameObjects" : "BD 4/4/2019 15:12",
		"drawWorld" : "WoC 4/8/2019 12:00",
		"gameObjects" : "BD 4/4/2019 12:08",
		"gameObjects:" : "BD 4/4/2019 12:08",
		"handleCollisions" : "WoC 4/8/2019 11:22",
		"handlesKeyboard:" : "WoC 4/5/2019 13:34",
		"initialize" : "WoC 4/10/2019 15:04",
		"initializeBackground" : "BD 4/4/2019 12:12",
		"initializeCoins" : "WoC 4/10/2019 15:04",
		"initializeGround" : "WoC 4/5/2019 11:01",
		"initializeGumbas" : "WoC 4/8/2019 10:13",
		"initializeMario" : "WoC 4/8/2019 09:43",
		"initializePlatforms" : "WoC 4/10/2019 10:12",
		"initializeStyle" : "BD 4/4/2019 14:26",
		"isWithin:toVisibleSection:" : "WoC 4/5/2019 10:54",
		"keyDown:" : "WoC 4/5/2019 13:44",
		"keyUp:" : "WoC 4/5/2019 13:45",
		"keyboardListener" : "WoC 4/5/2019 13:43",
		"keyboardListener:" : "WoC 4/5/2019 13:43",
		"mario" : "BD 4/4/2019 12:08",
		"mario:" : "BD 4/4/2019 12:08",
		"moveGameObjects" : "WoC 4/8/2019 12:00",
		"moveNPCs" : "WoC 4/9/2019 12:02",
		"npcs" : "WoC 4/5/2019 15:36",
		"npcs:" : "WoC 4/5/2019 15:36",
		"physics" : "WoC 4/5/2019 10:49",
		"physics:" : "WoC 4/5/2019 10:49",
		"simulateStep" : "WoC 4/9/2019 12:12",
		"step" : "WoC 4/8/2019 12:00",
		"stepTime" : "BD 4/4/2019 12:36",
		"translatedBounds" : "WoC 4/5/2019 10:55",
		"updateOffset" : "WoC 4/5/2019 11:20" } }
